unpaginate/__init__.py
unpaginate/_pagination.py
unpaginate/_stop.py
unpaginate/_unpaginate.py
unpaginate/py.typed
unpaginate-0.1.0.dist-info/METADATA
unpaginate-0.1.0.dist-info/WHEEL
unpaginate-0.1.0.dist-info/licenses/LICENSE.txt
unpaginate-0.1.0.dist-info/RECORD
