Metadata-Version: 2.3
Name: unpaginate
Version: 0.1.0
Summary: Chain calls of paginated APIs
Project-URL: Homepage, https://github.com/rogdham/unpaginate
Project-URL: Documentation, https://unpaginate.rogdham.net/
Project-URL: Source, https://github.com/rogdham/unpaginate
Author-email: Rogdham <contact@rogdham.net>
License: The MIT License (MIT)
License-File: LICENSE.txt
Keywords: api,chain,iterable,page,paginated,pagination
Classifier: Development Status :: 3 - Alpha
Classifier: License :: OSI Approved :: MIT License
Classifier: Operating System :: OS Independent
Classifier: Programming Language :: Python
Classifier: Programming Language :: Python :: 3
Classifier: Programming Language :: Python :: 3 :: Only
Classifier: Programming Language :: Python :: 3.8
Classifier: Programming Language :: Python :: 3.9
Classifier: Programming Language :: Python :: 3.10
Classifier: Programming Language :: Python :: 3.11
Classifier: Programming Language :: Python :: 3.12
Classifier: Topic :: Utilities
Requires-Python: >=3.8
Requires-Dist: typing-extensions>=4.11.0; python_version < '3.13'
